{
  "updatedAt": 1784134370468,
  "items": [
    {
      "title": "1 an après Un ours dans le Jura, voici la première photo et la date de sortie du nouveau film de Franck Dubosc, 5H48 : Place des Martyrs !",
      "link": "https://www.allocine.fr/article/fichearticle_gen_carticle=1000213390.html",
      "desc": "La date de sortie de \"5H48 : Place des Martyrs\", le nouveau film de Franck Dubosc vient d'être annoncée. Rendez-vous au cinéma en novembre 2",
      "isAI": false
    },
    {
      "title": "Un Si Grand Soleil en avance : résumé de l’épisode du jeudi 16 juillet juillet 2026 [SPOILERS]",
      "link": "https://www.allocine.fr/article/fichearticle_gen_carticle=1000213379.html",
      "desc": "Dans le prochain épisode de \"Un Si Grand Soleil\"... Tandis que Alain et Elisabeth sont interrogés, Bio soins porte plainte contre L. Cosméti",
      "isAI": false
    },
    {
      "title": "Box-office France : Vaiana surpasse-t-elle Toy Story 5 ?",
      "link": "https://www.allocine.fr/article/fichearticle_gen_carticle=1000213399.html",
      "desc": "Découvrez les chiffres du box-office français pour la semaine du 8 au 14 juillet 2026.",
      "isAI": false
    },
    {
      "title": "The Batman 2 : une bonne et une mauvaise nouvelle pour la suite très attendue avec Robert Pattinson",
      "link": "https://www.allocine.fr/article/fichearticle_gen_carticle=1000213375.html",
      "desc": "La très attendue suite de \"The Batman\" est enfin en tournage, et Matt Reeves le prouve avec un teaser montrant Robert Pattinson dans le cost",
      "isAI": false
    },
    {
      "title": "NCIS : \"Ce sera un retour passionnant\"... Michael Weatherly (DiNozzo) rassure les fans sur son comeback dans la série après 10 ans d'absence",
      "link": "https://www.allocine.fr/article/fichearticle_gen_carticle=1000213383.html",
      "desc": "A l'occasion d'une convention, Michael Weatherly en a dit un peu plus sur le retour de Tony DiNozzo dans la saison 24 de \"NCIS : Enquêtes Sp",
      "isAI": false
    },
    {
      "title": "Plus belle la vie : Thomas en grand danger dans la maison des Kepler ?",
      "link": "https://www.allocine.fr/article/fichearticle_gen_carticle=1000213296.html",
      "desc": "Depuis plusieurs jours dans \"Plus belle la vie, encore plus belle\", Thomas et Gabriel ont emménagé dans la villa de Vanessa Kepler. Mais dep",
      "isAI": false
    }
  ]
}