{
  "updatedAt": 1784047477492,
  "items": [
    {
      "title": "C'est l'une des fins les plus mémorables du cinéma : il y a 31 ans, sa révélation finale nous a scotchés sur place",
      "link": "https://www.allocine.fr/article/fichearticle_gen_carticle=1000212953.html",
      "desc": "Cette oeuvre a redéfini à elle seule la notion de révélation finale, laissant des millions de spectateurs scotchés devant l'écran. Retour su",
      "isAI": false
    },
    {
      "title": "Un Si Grand Soleil en avance : résumé de l’épisode du mercredi 15 juillet 2026 [SPOILERS]",
      "link": "https://www.allocine.fr/article/fichearticle_gen_carticle=1000212726.html",
      "desc": "Dans le prochain épisode de \"Un Si Grand Soleil\"... Tandis que Alain est arrêté, Clara harcèle Salomé.",
      "isAI": false
    },
    {
      "title": "\"Le meilleur de la franchise ! Explosif !\" : noté 3,6 sur 5, c'est le meilleur film de Dwayne Johnson !",
      "link": "https://www.allocine.fr/article/fichearticle_gen_carticle=1000211347.html",
      "desc": "Dwayne Johnson est actuellement à l'affiche du film \"Vaiana, la légende du bout du monde\". L'occasion de découvrir l'œuvre préférée des spec",
      "isAI": false
    },
    {
      "title": "La Petite maison dans la prairie version Netflix : quel personnage iconique va apparaître dans la saison 2 ?",
      "link": "https://www.allocine.fr/article/fichearticle_gen_carticle=1000213038.html",
      "desc": "Renouvelée avant même la diffusion de la saison 1 et déjà en tournage, la saison 2 de \"La Petite maison dans la prairie\" introduira un perso",
      "isAI": false
    },
    {
      "title": "Plus belle la vie : entre Laura et Dassari, qui va mourir ?",
      "link": "https://www.allocine.fr/article/fichearticle_gen_carticle=1000213008.html",
      "desc": "Dans l'épisode de \"Plus belle la vie, encore plus belle\" diffusé ce mardi matin, Laura va se retrouver dans une situation délicate. Va-t-ell",
      "isAI": false
    },
    {
      "title": "Un Si Grand Soleil : \"Elle n'hésite pas à manipuler les gens\"... Delphine Wespiser (Miss France) se confie sur son arrivée dans la série",
      "link": "https://www.allocine.fr/article/fichearticle_gen_carticle=1000213034.html",
      "desc": "L'ancienne Miss France Delphine Wespiser va faire son entrée dans \"Un Si Grand Soleil\" ce mardi 14 juillet. A cette occasion, la comédienne ",
      "isAI": false
    }
  ]
}