{
  "updatedAt": 1784013840383,
  "items": [
    {
      "title": "House of the Dragon",
      "season": "En cours",
      "date": "2022-08-21",
      "link": "https://www.themoviedb.org/tv/94997",
      "image": "https://image.tmdb.org/t/p/w500/lP73xk4HGJ9CPxDWouzKzK6j82o.jpg",
      "desc": "Près de 200 ans avant les évènements de Game of Thrones, le continent de Westero..."
    },
    {
      "title": "Mushoku Tensei: Jobless Reincarnation",
      "season": "En cours",
      "date": "2021-01-11",
      "link": "https://www.themoviedb.org/tv/94664",
      "image": "https://image.tmdb.org/t/p/w500/sviEqFIPJW5gFtuYy8XyE0Uscid.jpg",
      "desc": "« Ici, je vais me transcender ! » Un anonyme de 34 ans, célibataire endurci, rec..."
    },
    {
      "title": "Silo",
      "season": "En cours",
      "date": "2023-05-04",
      "link": "https://www.themoviedb.org/tv/125988",
      "image": "https://image.tmdb.org/t/p/w500/zGMLj5ZTybGpgYtNnDbMbN1rOcp.jpg",
      "desc": "Dans un monde futur dévasté et toxique, des milliers de survivants habitent un g..."
    },
    {
      "title": "Chainsmoker Cat",
      "season": "En cours",
      "date": "2026-07-03",
      "link": "https://www.themoviedb.org/tv/312949",
      "image": "https://image.tmdb.org/t/p/w500/1OEYjA3bpPlXNPwV51WJhGWx8Mk.jpg",
      "desc": "Entre loyer impayé, emplois perdus et dépendance à la cigarette, Yani la fille-c..."
    },
    {
      "title": "Renegade Immortal",
      "season": "En cours",
      "date": "2023-09-25",
      "link": "https://www.themoviedb.org/tv/223911",
      "image": "https://image.tmdb.org/t/p/w500/mCt5qgkOYEvuHSiSwNByMv6LMoB.jpg",
      "desc": "Il raconte l'histoire de Wang Lin, un jeune homme ordinaire vivant à la campagne..."
    }
  ]
}